aiothreads/__init__.py
aiothreads/coroutine_waiter.py
aiothreads/iterator_wrapper.py
aiothreads/new_thread.py
aiothreads/py.typed
aiothreads/threaded_iterable.py
aiothreads/threads.py
aiothreads/types.py
aiothreads-1.0.0.dist-info/METADATA
aiothreads-1.0.0.dist-info/WHEEL
aiothreads-1.0.0.dist-info/licenses/LICENSE
aiothreads-1.0.0.dist-info/RECORD
