Metadata-Version: 2.4
Name: aiothreads
Version: 0.1.0
Summary: glue between asyn and thread worlds
Requires-Python: >=3.10
